opal_server/__init__.py
opal_server/cli.py
opal_server/config.py
opal_server/main.py
opal_server/publisher.py
opal_server/pubsub.py
opal_server/server.py
opal_server/data/__init__.py
opal_server/data/api.py
opal_server/data/data_update_publisher.py
opal_server/deps/__init__.py
opal_server/deps/authentication.py
opal_server/policy/__init__.py
opal_server/policy/bundles/__init__.py
opal_server/policy/bundles/api.py
opal_server/policy/github_webhook/__init__.py
opal_server/policy/github_webhook/api.py
opal_server/policy/github_webhook/deps.py
opal_server/policy/github_webhook/listener.py
opal_server/policy/watcher/__init__.py
opal_server/policy/watcher/callbacks.py
opal_server/policy/watcher/factory.py
opal_server/policy/watcher/task.py
opal_server/security/__init__.py
opal_server/security/api.py
opal_server/security/jwks.py
opal_server_fork-0.1.25.dist-info/LICENSE
opal_server_fork-0.1.25.dist-info/METADATA
opal_server_fork-0.1.25.dist-info/WHEEL
opal_server_fork-0.1.25.dist-info/entry_points.txt
opal_server_fork-0.1.25.dist-info/top_level.txt
opal_server_fork-0.1.25.dist-info/RECORD
